tests
webcrawler_plus
