Metadata-Version: 1.0
Name: web-crawler-plus
Version: 0.9.14
Summary: A micro-framework to crawl the web pages with crawlers configs. It can use MongoDB, Elasticsearch and Solr databases to cache and save the extracted data.
Home-page: https://github.com/invanatech/web-crawler-plus
Author: Ravi Raja Merugu
Author-email: rrmerugu@gmail.com
License: UNKNOWN
Platform: UNKNOWN
